LICENSE.txt
MANIFEST.in
README.md
setup.py
django_email_analytics.egg-info/PKG-INFO
django_email_analytics.egg-info/SOURCES.txt
django_email_analytics.egg-info/dependency_links.txt
django_email_analytics.egg-info/requires.txt
django_email_analytics.egg-info/top_level.txt
docs/README.rst
emailanalytics/__init__.py
emailanalytics/backends.py
emailanalytics/tests.py
emailanalytics/text_processing.py