Metadata-Version: 1.0
Name: django-email-analytics
Version: 0.2
Summary: Adds Google Analytics tracking to emails sent with Django.
Home-page: https://github.com/grokcode/django-email-analytics
Author: Jess Johnson
Author-email: jess@grokcode.com
License: LICENSE.txt
Platform: UNKNOWN
